AUTHORS
ChangeLog
MANIFEST.in
README
README.md
openstack-common.conf
requirements.txt
setup.cfg
setup.py
test-requirements.txt
tox.ini
docs/gitshelf-ae1.yml
docs/gitshelf-aw2.yml
docs/gitshelf-link-absolute.yml
docs/gitshelf-link.yml
docs/gitshelf-paas-core-aw2.yml
docs/gitshelf-w-tokens.yml
docs/gitshelf.yml
docs/token-test/gitshelf.yml
gitshelf/__init__.py
gitshelf/book.py
gitshelf/exceptions.py
gitshelf/shell.py
gitshelf/utils.py
gitshelf/version.py
gitshelf.egg-info/PKG-INFO
gitshelf.egg-info/SOURCES.txt
gitshelf.egg-info/dependency_links.txt
gitshelf.egg-info/entry_points.txt
gitshelf.egg-info/not-zip-safe
gitshelf.egg-info/requires.txt
gitshelf.egg-info/top_level.txt
gitshelf/cli/__init__.py
gitshelf/cli/diff.py
gitshelf/cli/discover.py
gitshelf/cli/install.py
gitshelf/cli/status.py
gitshelf/openstack/__init__.py
gitshelf/openstack/common/__init__.py
gitshelf/openstack/common/setup.py
gitshelf/openstack/common/version.py
gitshelf/tests/__init__.py