Metadata-Version: 1.1
Name: gitshelf
Version: 0.0.4
Summary: Manage a shelf full of git repos
Home-page: https://github.com/gitshelf/gitshelf
Author: Simon McCartney
Author-email: simon.mccartnet@hp.com
License: UNKNOWN
Platform: UNKNOWN
Classifier: Environment :: Console
Classifier: Intended Audience :: Information Technology
Classifier: Intended Audience :: System Administrators
Classifier: License :: OSI Approved :: Apache Software License
Classifier: Operating System :: POSIX :: Linux
Classifier: Programming Language :: Python :: 2.7
Classifier: Programming Language :: Python :: 2.6
